command_seq_reader.py
pyparsing_helper.py
setup.py
pyparsing_helper.egg-info/PKG-INFO
pyparsing_helper.egg-info/SOURCES.txt
pyparsing_helper.egg-info/dependency_links.txt
pyparsing_helper.egg-info/entry_points.txt
pyparsing_helper.egg-info/requires.txt
pyparsing_helper.egg-info/top_level.txt